shared_security/__init__.py
shared_security/admin.py
shared_security/apps.py
shared_security/authentication.py
shared_security/helpers.py
shared_security/models.py
shared_security/tests.py
shared_security/views.py
shared_security/api/__init__.py
shared_security/api/urls.py
shared_security/api/serializers/__init__.py
shared_security/api/serializers/errors.py
shared_security/api/serializers/users.py
shared_security/api/views/__init__.py
shared_security/api/views/users.py
shared_security/migrations/0001_initial.py
shared_security/migrations/__init__.py
django_external_jwttoken_shared_security-0.1.dist-info/METADATA
django_external_jwttoken_shared_security-0.1.dist-info/WHEEL
django_external_jwttoken_shared_security-0.1.dist-info/top_level.txt
django_external_jwttoken_shared_security-0.1.dist-info/RECORD
