Metadata-Version: 2.1
Name: django-external-jwttoken-shared-security
Version: 0.1
Summary: A Django app is used to manage django auth using a token from a external source.
Home-page: https://www.example.com/
Author: Eduardo Miguel Hernández
Author-email: aisco@gmail.com
License: BSD-3-Clause
Classifier: Environment :: Web Environment
Classifier: Framework :: Django
Classifier: Framework :: Django :: 4.0
Classifier: Intended Audience :: Developers
Classifier: License :: OSI Approved :: BSD License
Classifier: Operating System :: OS Independent
Classifier: Programming Language :: Python
Classifier: Programming Language :: Python :: 3
Classifier: Programming Language :: Python :: 3 :: Only
Classifier: Programming Language :: Python :: 3.6
Classifier: Programming Language :: Python :: 3.7
Classifier: Programming Language :: Python :: 3.8
Classifier: Programming Language :: Python :: 3.9
Classifier: Topic :: Internet :: WWW/HTTP
Classifier: Topic :: Internet :: WWW/HTTP :: Dynamic Content
Requires-Python: >=3.6
Requires-Dist: Django >=4.0
Requires-Dist: djangorestframework >=3.13.1
Requires-Dist: drf-spectacular >=0.23.1
